admin_appmenu/__init__.py
admin_appmenu/util.py
admin_appmenu/templates/admin_appmenu/navigation.html
admin_appmenu/templatetags/__init__.py
admin_appmenu/templatetags/navigation.py
admin_appmenu/tests/__init__.py
admin_appmenu/tests/admin.py
admin_appmenu/tests/custom_admin_urls.py
admin_appmenu/tests/models.py
admin_appmenu/tests/requirements.txt
admin_appmenu/tests/settings.py
admin_appmenu/tests/test_templatetags.py
admin_appmenu/tests/test_version.py
admin_appmenu/tests/urls.py
admin_appmenu/tests/templates/admin_appmenu/navigation.html
django_admin_appmenu-1.0.0.dist-info/DESCRIPTION.rst
django_admin_appmenu-1.0.0.dist-info/METADATA
django_admin_appmenu-1.0.0.dist-info/RECORD
django_admin_appmenu-1.0.0.dist-info/WHEEL
django_admin_appmenu-1.0.0.dist-info/metadata.json
django_admin_appmenu-1.0.0.dist-info/top_level.txt
