Metadata-Version: 2.0
Name: django-admin-appmenu
Version: 1.0.0
Summary: Templatetag to render an application menu in the Django admin.
Home-page: http://github.com/collab-project/django-admin-appmenu
Author: Collab
Author-email: info@collab.nl
License: MIT
Platform: UNKNOWN
Classifier: Development Status :: 5 - Production/Stable
Classifier: Framework :: Django
Classifier: Intended Audience :: Developers
Classifier: License :: OSI Approved :: MIT License
Classifier: Operating System :: OS Independent
Classifier: Topic :: Software Development
Classifier: Programming Language :: Python :: 2
Classifier: Programming Language :: Python :: 2.7
Classifier: Programming Language :: Python :: 3
Classifier: Programming Language :: Python :: 3.3
Classifier: Programming Language :: Python :: 3.4
